pystreamable/StreamableApi.py
pystreamable/__init__.py
pystreamable/exceptions.py
pystreamable/utils.py
pystreamable-1.0.1.dist-info/DESCRIPTION.rst
pystreamable-1.0.1.dist-info/METADATA
pystreamable-1.0.1.dist-info/RECORD
pystreamable-1.0.1.dist-info/WHEEL
pystreamable-1.0.1.dist-info/metadata.json
pystreamable-1.0.1.dist-info/top_level.txt
