Metadata-Version: 2.0
Name: pystreamable
Version: 1.0.1
Summary: streamable.com API wrapper
Home-page: https://github.com/jernejovc/pystreamable
Author: Matej Repinc
Author-email: mrepinc@gmail.com
License: MIT
Keywords: streamable streamable.com api wrapper
Platform: UNKNOWN
Classifier: Development Status :: 4 - Beta
Classifier: Topic :: Utilities
Classifier: License :: OSI Approved :: MIT License
